{
    "Ar36": {
        "error": 9.682730905299923e-09,
        "error_type": "",
        "fit": "previous",
        "references": [
            {
                "exclude": false,
                "record_id": "ba-01-n-4650"
            }
        ],
        "value": 3.685677325316935e-07
    },
    "Ar37": {
        "error": 2.1381106980422757e-07,
        "error_type": "",
        "fit": "previous",
        "references": [
            {
                "exclude": false,
                "record_id": "ba-01-n-4650"
            }
        ],
        "value": 1.4043797608596037e-07
    },
    "Ar38": {
        "error": 1.5241754494669042e-07,
        "error_type": "",
        "fit": "previous",
        "references": [
            {
                "exclude": false,
                "record_id": "ba-01-n-4650"
            }
        ],
        "value": 4.0500486440569575e-07
    },
    "Ar39": {
        "error": 1.9372465080458095e-07,
        "error_type": "",
        "fit": "previous",
        "references": [
            {
                "exclude": false,
                "record_id": "ba-01-n-4650"
            }
        ],
        "value": 6.952904056417959e-07
    },
    "Ar40": {
        "error": 9.643224289726707e-07,
        "error_type": "",
        "fit": "previous",
        "references": [
            {
                "exclude": false,
                "record_id": "ba-01-n-4650"
            }
        ],
        "value": 0.00010154950935551692
    }
}