{
    "Ar36": {
        "error": 1.0712870830303591e-08,
        "error_type": "",
        "fit": "previous",
        "references": [
            {
                "exclude": false,
                "record_id": "ba-01-n-4346"
            }
        ],
        "value": 3.781125302733718e-07
    },
    "Ar37": {
        "error": 1.2742629790715734e-07,
        "error_type": "",
        "fit": "previous",
        "references": [
            {
                "exclude": false,
                "record_id": "ba-01-n-4346"
            }
        ],
        "value": 3.0086982849326983e-07
    },
    "Ar38": {
        "error": 1.6128340166930685e-07,
        "error_type": "",
        "fit": "previous",
        "references": [
            {
                "exclude": false,
                "record_id": "ba-01-n-4346"
            }
        ],
        "value": -1.6826806235324908e-07
    },
    "Ar39": {
        "error": 2.3538667099678362e-07,
        "error_type": "",
        "fit": "previous",
        "references": [
            {
                "exclude": false,
                "record_id": "ba-01-n-4346"
            }
        ],
        "value": 1.315638977308046e-06
    },
    "Ar40": {
        "error": 6.638592795868121e-07,
        "error_type": "",
        "fit": "previous",
        "references": [
            {
                "exclude": false,
                "record_id": "ba-01-n-4346"
            }
        ],
        "value": 9.062555225932133e-05
    }
}