{
    "Ar36": {
        "error": 1.1693846294466775e-07,
        "error_type": "",
        "fit": "previous",
        "references": [
            {
                "exclude": false,
                "record_id": "ba-01-n-3987"
            }
        ],
        "value": 1.8056940379538478e-07
    },
    "Ar37": {
        "error": 1.239045209330718e-07,
        "error_type": "",
        "fit": "previous",
        "references": [
            {
                "exclude": false,
                "record_id": "ba-01-n-3987"
            }
        ],
        "value": 1.2879976180745514e-08
    },
    "Ar38": {
        "error": 1.4146468099610456e-07,
        "error_type": "",
        "fit": "previous",
        "references": [
            {
                "exclude": false,
                "record_id": "ba-01-n-3987"
            }
        ],
        "value": 2.1440869701284114e-07
    },
    "Ar39": {
        "error": 1.9862940544039002e-07,
        "error_type": "",
        "fit": "previous",
        "references": [
            {
                "exclude": false,
                "record_id": "ba-01-n-3987"
            }
        ],
        "value": 5.362303445896724e-07
    },
    "Ar40": {
        "error": 1.0956717533826246e-06,
        "error_type": "",
        "fit": "previous",
        "references": [
            {
                "exclude": false,
                "record_id": "ba-01-n-3987"
            }
        ],
        "value": 5.973776915565246e-05
    }
}