{
    "Ar36": {
        "error": 4.278128521560281e-07,
        "error_type": "SEM",
        "filter_outliers_dict": {
            "filter_outliers": true,
            "iterations": 1,
            "std_devs": 2
        },
        "fit": "linear",
        "value": 0.00016533786458145766
    },
    "Ar37": {
        "error": 1.9211088544490374e-07,
        "error_type": "SEM",
        "filter_outliers_dict": {
            "filter_outliers": true,
            "iterations": 1,
            "std_devs": 2
        },
        "fit": "linear",
        "value": -1.5093664458341784e-06
    },
    "Ar38": {
        "error": 1.7981716890237499e-07,
        "error_type": "SEM",
        "filter_outliers_dict": {
            "filter_outliers": true,
            "iterations": 1,
            "std_devs": 2
        },
        "fit": "linear",
        "value": 2.7252943676325954e-05
    },
    "Ar39": {
        "error": 4.091564885627544e-06,
        "error_type": "SEM",
        "filter_outliers_dict": {
            "filter_outliers": true,
            "iterations": 1,
            "std_devs": 2
        },
        "fit": "linear",
        "value": 4.2897515538477325e-05
    },
    "Ar40": {
        "error": 6.752346232145456e-06,
        "error_type": "SEM",
        "filter_outliers_dict": {
            "filter_outliers": true,
            "iterations": 1,
            "std_devs": 2
        },
        "fit": "parabolic",
        "value": 0.05023597567492881
    }
}