{
    "Ar36": {
        "error": 8.827616309038012e-09,
        "error_type": "",
        "fit": "previous",
        "references": [
            {
                "exclude": false,
                "record_id": "ba-01-n-4585"
            }
        ],
        "value": 3.525024962028423e-07
    },
    "Ar37": {
        "error": 1.8729356889464388e-07,
        "error_type": "",
        "fit": "previous",
        "references": [
            {
                "exclude": false,
                "record_id": "ba-01-n-4585"
            }
        ],
        "value": -2.002082529469897e-07
    },
    "Ar38": {
        "error": 1.5139190649498362e-07,
        "error_type": "",
        "fit": "previous",
        "references": [
            {
                "exclude": false,
                "record_id": "ba-01-n-4585"
            }
        ],
        "value": 3.054824155109179e-07
    },
    "Ar39": {
        "error": 1.69854022077075e-07,
        "error_type": "",
        "fit": "previous",
        "references": [
            {
                "exclude": false,
                "record_id": "ba-01-n-4585"
            }
        ],
        "value": 1.1227779738116843e-07
    },
    "Ar40": {
        "error": 7.667827016421882e-07,
        "error_type": "",
        "fit": "previous",
        "references": [
            {
                "exclude": false,
                "record_id": "ba-01-n-4585"
            }
        ],
        "value": 9.667858086306293e-05
    }
}