{
    "Ar36": {
        "error": 9.348323384904484e-09,
        "error_type": "",
        "fit": "previous",
        "references": [
            {
                "exclude": false,
                "record_id": "ba-01-n-4475"
            }
        ],
        "value": 4.1372981691441945e-07
    },
    "Ar37": {
        "error": 1.652328443562416e-07,
        "error_type": "",
        "fit": "previous",
        "references": [
            {
                "exclude": false,
                "record_id": "ba-01-n-4475"
            }
        ],
        "value": -2.1585624097338442e-07
    },
    "Ar38": {
        "error": 1.3707917429655947e-07,
        "error_type": "",
        "fit": "previous",
        "references": [
            {
                "exclude": false,
                "record_id": "ba-01-n-4475"
            }
        ],
        "value": 8.614447320820745e-08
    },
    "Ar39": {
        "error": 2.0403638129020473e-07,
        "error_type": "",
        "fit": "previous",
        "references": [
            {
                "exclude": false,
                "record_id": "ba-01-n-4475"
            }
        ],
        "value": 2.375161596331816e-07
    },
    "Ar40": {
        "error": 8.53706206016492e-07,
        "error_type": "",
        "fit": "previous",
        "references": [
            {
                "exclude": false,
                "record_id": "ba-01-n-4475"
            }
        ],
        "value": 0.00010465366307699509
    }
}