{
    "Ar36": {
        "error": 9.056216512025925e-09,
        "error_type": "",
        "fit": "previous",
        "references": [
            {
                "exclude": false,
                "record_id": "ba-01-n-4395"
            }
        ],
        "value": 3.1120966946500765e-07
    },
    "Ar37": {
        "error": 1.980796234755096e-07,
        "error_type": "",
        "fit": "previous",
        "references": [
            {
                "exclude": false,
                "record_id": "ba-01-n-4395"
            }
        ],
        "value": 3.3311723073023205e-07
    },
    "Ar38": {
        "error": 2.417629297040484e-07,
        "error_type": "",
        "fit": "previous",
        "references": [
            {
                "exclude": false,
                "record_id": "ba-01-n-4395"
            }
        ],
        "value": 3.493063295491871e-07
    },
    "Ar39": {
        "error": 1.4801543237990796e-07,
        "error_type": "",
        "fit": "previous",
        "references": [
            {
                "exclude": false,
                "record_id": "ba-01-n-4395"
            }
        ],
        "value": 6.484976381483692e-07
    },
    "Ar40": {
        "error": 9.052191118632289e-07,
        "error_type": "",
        "fit": "previous",
        "references": [
            {
                "exclude": false,
                "record_id": "ba-01-n-4395"
            }
        ],
        "value": 7.553682057398217e-05
    }
}