{
    "Ar36": {
        "error": 1.2847165929952138e-08,
        "error_type": "",
        "fit": "previous",
        "references": [
            {
                "exclude": false,
                "record_id": "ba-01-n-4165"
            }
        ],
        "value": 2.838708816971486e-07
    },
    "Ar37": {
        "error": 1.7868263643610067e-07,
        "error_type": "",
        "fit": "previous",
        "references": [
            {
                "exclude": false,
                "record_id": "ba-01-n-4165"
            }
        ],
        "value": -2.6978792307643272e-08
    },
    "Ar38": {
        "error": 2.0249611579483344e-07,
        "error_type": "",
        "fit": "previous",
        "references": [
            {
                "exclude": false,
                "record_id": "ba-01-n-4165"
            }
        ],
        "value": 4.319044610023137e-07
    },
    "Ar39": {
        "error": 1.7512061539289165e-06,
        "error_type": "",
        "fit": "previous",
        "references": [
            {
                "exclude": false,
                "record_id": "ba-01-n-4165"
            }
        ],
        "value": 1.9076061395920583e-07
    },
    "Ar40": {
        "error": 1.8259324397240224e-06,
        "error_type": "",
        "fit": "previous",
        "references": [
            {
                "exclude": false,
                "record_id": "ba-01-n-4165"
            }
        ],
        "value": 2.865207310601086e-05
    }
}